oneNeuron/__init__.py
oneNeuron/perceptron.py
utils/__init__.py
utils/utils.py
oneNeuron_perceptron_pypi_guptabhishek8-0.0.4.dist-info/LICENSE
oneNeuron_perceptron_pypi_guptabhishek8-0.0.4.dist-info/METADATA
oneNeuron_perceptron_pypi_guptabhishek8-0.0.4.dist-info/WHEEL
oneNeuron_perceptron_pypi_guptabhishek8-0.0.4.dist-info/top_level.txt
oneNeuron_perceptron_pypi_guptabhishek8-0.0.4.dist-info/RECORD
