Metadata-Version: 2.1
Name: oneNeuron-perceptron-pypi-guptabhishek8
Version: 0.0.4
Summary: its a implementation of Perceptron
Home-page: https://github.com/guptabhishek8/oneNeuron_perceptron_pypi
Author: guptabhishek8
Author-email: guptabhishek8@gmail.com
License: UNKNOWN
Project-URL: Bug Tracker, https://github.com/guptabhishek8/oneNeuron_perceptron_pypi/issues
Platform: UNKNOWN
Classifier: Programming Language :: Python :: 3
Classifier: License :: OSI Approved :: MIT License
Classifier: Operating System :: OS Independent
Requires-Python: >=3.7
License-File: LICENSE
Requires-Dist: numpy
Requires-Dist: tqdm
Requires-Dist: pandas
Requires-Dist: joblib
Requires-Dist: matplotlib.pyplot
Requires-Dist: matplotlib.colors
